nonebot_plugin_ai_groupmate/SourceHanSans.otf
nonebot_plugin_ai_groupmate/__init__.py
nonebot_plugin_ai_groupmate/agent/__init__.py
nonebot_plugin_ai_groupmate/agent/上升.jpg
nonebot_plugin_ai_groupmate/agent/下降.jpg
nonebot_plugin_ai_groupmate/config.py
nonebot_plugin_ai_groupmate/migrations/6a6a44d58ced_first_revision.py
nonebot_plugin_ai_groupmate/milvus/__init__.py
nonebot_plugin_ai_groupmate/model.py
nonebot_plugin_ai_groupmate/stop_words.txt
nonebot_plugin_ai_groupmate/utils.py
nonebot_plugin_ai_groupmate/vlm.py
nonebot_plugin_ai_groupmate-1.0.2.dist-info/WHEEL
nonebot_plugin_ai_groupmate-1.0.2.dist-info/METADATA
nonebot_plugin_ai_groupmate-1.0.2.dist-info/RECORD
