Metadata-Version: 2.3
Name: nonebot-plugin-ai-groupmate
Version: 1.0.2
Summary: ai 群友
Author: yaowan233
Author-email: yaowan233 <572473053@qq.com>
Requires-Dist: datasets>=3.4.1
Requires-Dist: einops>=0.8.1
Requires-Dist: flagembedding>=1.3.5
Requires-Dist: jieba>=0.42.1
Requires-Dist: langchain>=1.1.0
Requires-Dist: langchain-openai>=1.0.3
Requires-Dist: langchain-tavily>=0.2.13
Requires-Dist: matplotlib>=3.10.1
Requires-Dist: nonebot-plugin-alconna>=0.60.3
Requires-Dist: nonebot-plugin-apscheduler>=0.5.0
Requires-Dist: nonebot-plugin-localstore>=0.7.4
Requires-Dist: nonebot-plugin-orm>=0.8.2
Requires-Dist: nonebot-plugin-session>=0.3.2
Requires-Dist: nonebot-plugin-uninfo>=0.10.0
Requires-Dist: nonebot2>=2.4.4
Requires-Dist: numpy>=2
Requires-Dist: ollama>=0.6.1
Requires-Dist: peft>=0.15.0
Requires-Dist: pillow>=11.1.0
Requires-Dist: pymilvus[milvus-lite,model]>=2.6.3
Requires-Dist: simpleeval>=1.0.3
Requires-Dist: tiktoken>=0.12.0
Requires-Dist: timm>=1.0.22
Requires-Dist: torch>=2.7.0
Requires-Dist: torchaudio>=2.7.0
Requires-Dist: torchvision>=0.22.0
Requires-Dist: wordcloud>=1.9.4
Requires-Python: >=3.10, <3.14
Project-URL: Homepage, https://github.com/yaowan233/nonebot-plugin-ai-groupmate
Project-URL: Repository, https://github.com/yaowan233/nonebot-plugin-ai-groupmate
